[
  {"ma_nganh": "7720101", "ten": "Y khoa", "nam": 2025, "diem_thpt": 20.5, "diem_hocba": 24.0, "diem_dgnl": 650, "diem_vsat": 290},
  {"ma_nganh": "7720501", "ten": "Răng - Hàm - Mặt", "nam": 2025, "diem_thpt": 20.5, "diem_hocba": 24.0, "diem_dgnl": 650, "diem_vsat": 290},
  {"ma_nganh": "7720201", "ten": "Dược học", "nam": 2025, "diem_thpt": 19.0, "diem_hocba": 22.5, "diem_dgnl": 600, "diem_vsat": 270},
  {"ma_nganh": "7720110", "ten": "Y học dự phòng", "nam": 2025, "diem_thpt": 17.0, "diem_hocba": 20.5, "diem_dgnl": 550, "diem_vsat": 225},
  {"ma_nganh": "7720601", "ten": "Kỹ thuật xét nghiệm y học", "nam": 2025, "diem_thpt": 17.0, "diem_hocba": 20.5, "diem_dgnl": 550, "diem_vsat": 225},
  {"ma_nganh": "7720602", "ten": "Kỹ thuật hình ảnh y học", "nam": 2025, "diem_thpt": 17.0, "diem_hocba": 20.5, "diem_dgnl": 550, "diem_vsat": 225},
  {"ma_nganh": "7720301", "ten": "Điều dưỡng", "nam": 2025, "diem_thpt": 17.0, "diem_hocba": 20.5, "diem_dgnl": 550, "diem_vsat": 225},
  {"ma_nganh": "7720802", "ten": "Quản lý bệnh viện", "nam": 2025, "diem_thpt": 15.0, "diem_hocba": 18.0, "diem_dgnl": 500, "diem_vsat": 225},
  {"ma_nganh": "7520212", "ten": "Kỹ thuật y sinh (Khoa học và công nghệ y khoa)", "nam": 2025, "diem_thpt": 15.0, "diem_hocba": 18.0, "diem_dgnl": 500, "diem_vsat": 225},
  {"ma_nganh": "7510205", "ten": "Công nghệ kỹ thuật ô tô", "nam": 2025, "diem_thpt": 15.0, "diem_hocba": 18.0, "diem_dgnl": 500, "diem_vsat": 225},
  {"ma_nganh": "7510205-01", "ten": "Công nghệ kỹ thuật ô tô (Chuyên ngành Ô tô điện)", "nam": 2025, "diem_thpt": 15.0, "diem_hocba": 18.0, "diem_dgnl": 500, "diem_vsat": 225},
  {"ma_nganh": "7520116", "ten": "Kỹ thuật cơ khí động lực", "nam": 2025, "diem_thpt": 15.0, "diem_hocba": 18.0, "diem_dgnl": 500, "diem_vsat": 225},
  {"ma_nganh": "7480201", "ten": "Công nghệ thông tin", "nam": 2025, "diem_thpt": 15.0, "diem_hocba": 18.0, "diem_dgnl": 500, "diem_vsat": 225},
  {"ma_nganh": "7480103", "ten": "Kỹ thuật phần mềm", "nam": 2025, "diem_thpt": 15.0, "diem_hocba": 18.0, "diem_dgnl": 500, "diem_vsat": 225},
  {"ma_nganh": "7480101", "ten": "Khoa học máy tính", "nam": 2025, "diem_thpt": 15.0, "diem_hocba": 18.0, "diem_dgnl": 500, "diem_vsat": 225},
  {"ma_nganh": "7480101-01", "ten": "Khoa học máy tính (Chuyên ngành Thiết kế vi mạch bán dẫn)", "nam": 2025, "diem_thpt": 15.0, "diem_hocba": 18.0, "diem_dgnl": 500, "diem_vsat": 225},
  {"ma_nganh": "7480102", "ten": "Mạng máy tính và truyền thông dữ liệu", "nam": 2025, "diem_thpt": 15.0, "diem_hocba": 18.0, "diem_dgnl": 500, "diem_vsat": 225},
  {"ma_nganh": "7480207", "ten": "Trí tuệ nhân tạo", "nam": 2025, "diem_thpt": 15.0, "diem_hocba": 18.0, "diem_dgnl": 500, "diem_vsat": 225},
  {"ma_nganh": "7510301", "ten": "Công nghệ kỹ thuật điện, điện tử", "nam": 2025, "diem_thpt": 15.0, "diem_hocba": 18.0, "diem_dgnl": 500, "diem_vsat": 225},
  {"ma_nganh": "7540101", "ten": "Công nghệ thực phẩm", "nam": 2025, "diem_thpt": 15.0, "diem_hocba": 18.0, "diem_dgnl": 500, "diem_vsat": 225},
  {"ma_nganh": "7510401", "ten": "Công nghệ kỹ thuật hóa học", "nam": 2025, "diem_thpt": 15.0, "diem_hocba": 18.0, "diem_dgnl": 500, "diem_vsat": 225},
  {"ma_nganh": "7340101", "ten": "Quản trị kinh doanh", "nam": 2025, "diem_thpt": 15.0, "diem_hocba": 18.0, "diem_dgnl": 500, "diem_vsat": 225},
  {"ma_nganh": "7340201", "ten": "Tài chính - ngân hàng", "nam": 2025, "diem_thpt": 15.0, "diem_hocba": 18.0, "diem_dgnl": 500, "diem_vsat": 225},
  {"ma_nganh": "7340301", "ten": "Kế toán", "nam": 2025, "diem_thpt": 15.0, "diem_hocba": 18.0, "diem_dgnl": 500, "diem_vsat": 225},
  {"ma_nganh": "7340115", "ten": "Marketing", "nam": 2025, "diem_thpt": 15.0, "diem_hocba": 18.0, "diem_dgnl": 500, "diem_vsat": 225},
  {"ma_nganh": "7340120", "ten": "Kinh doanh quốc tế", "nam": 2025, "diem_thpt": 15.0, "diem_hocba": 18.0, "diem_dgnl": 500, "diem_vsat": 225},
  {"ma_nganh": "7310109", "ten": "Kinh tế số", "nam": 2025, "diem_thpt": 15.0, "diem_hocba": 18.0, "diem_dgnl": 500, "diem_vsat": 225},
  {"ma_nganh": "7340122", "ten": "Thương mại điện tử", "nam": 2025, "diem_thpt": 15.0, "diem_hocba": 18.0, "diem_dgnl": 500, "diem_vsat": 225},
  {"ma_nganh": "7340116", "ten": "Bất động sản", "nam": 2025, "diem_thpt": 15.0, "diem_hocba": 18.0, "diem_dgnl": 500, "diem_vsat": 225},
  {"ma_nganh": "7510605", "ten": "Logistics và quản lý chuỗi cung ứng", "nam": 2025, "diem_thpt": 15.0, "diem_hocba": 18.0, "diem_dgnl": 500, "diem_vsat": 225},
  {"ma_nganh": "7510601", "ten": "Quản lý công nghiệp", "nam": 2025, "diem_thpt": 15.0, "diem_hocba": 18.0, "diem_dgnl": 500, "diem_vsat": 225},
  {"ma_nganh": "7320108", "ten": "Quan hệ công chúng (PR)", "nam": 2025, "diem_thpt": 15.0, "diem_hocba": 18.0, "diem_dgnl": 500, "diem_vsat": 225},
  {"ma_nganh": "7320104", "ten": "Truyền thông đa phương tiện", "nam": 2025, "diem_thpt": 15.0, "diem_hocba": 18.0, "diem_dgnl": 500, "diem_vsat": 225},
  {"ma_nganh": "7380101", "ten": "Luật", "nam": 2025, "diem_thpt": 15.0, "diem_hocba": 18.0, "diem_dgnl": 500, "diem_vsat": 225},
  {"ma_nganh": "7380107", "ten": "Luật Kinh tế", "nam": 2025, "diem_thpt": 15.0, "diem_hocba": 18.0, "diem_dgnl": 500, "diem_vsat": 225},
  {"ma_nganh": "7220201", "ten": "Ngôn ngữ Anh", "nam": 2025, "diem_thpt": 15.0, "diem_hocba": 18.0, "diem_dgnl": 500, "diem_vsat": 225},
  {"ma_nganh": "7810201", "ten": "Quản trị khách sạn", "nam": 2025, "diem_thpt": 15.0, "diem_hocba": 18.0, "diem_dgnl": 500, "diem_vsat": 225},
  {"ma_nganh": "7810202", "ten": "Quản trị nhà hàng và dịch vụ ăn uống", "nam": 2025, "diem_thpt": 15.0, "diem_hocba": 18.0, "diem_dgnl": 500, "diem_vsat": 225},
  {"ma_nganh": "7810103", "ten": "Quản trị dịch vụ du lịch và lữ hành", "nam": 2025, "diem_thpt": 15.0, "diem_hocba": 18.0, "diem_dgnl": 500, "diem_vsat": 225},
  {"ma_nganh": "7580101", "ten": "Kiến trúc", "nam": 2025, "diem_thpt": 15.0, "diem_hocba": 18.0, "diem_dgnl": 500, "diem_vsat": 225},
  {"ma_nganh": "7580201", "ten": "Kỹ thuật xây dựng", "nam": 2025, "diem_thpt": 15.0, "diem_hocba": 18.0, "diem_dgnl": 500, "diem_vsat": 225},
  {"ma_nganh": "7580302", "ten": "Quản lý xây dựng", "nam": 2025, "diem_thpt": 15.0, "diem_hocba": 18.0, "diem_dgnl": 500, "diem_vsat": 225},
  {"ma_nganh": "7580205", "ten": "Kỹ thuật xây dựng công trình giao thông", "nam": 2025, "diem_thpt": 15.0, "diem_hocba": 18.0, "diem_dgnl": 500, "diem_vsat": 225},
  {"ma_nganh": "7850101", "ten": "Quản lý tài nguyên và môi trường", "nam": 2025, "diem_thpt": 15.0, "diem_hocba": 18.0, "diem_dgnl": 500, "diem_vsat": 225},
  {"ma_nganh": "7850103", "ten": "Quản lý đất đai", "nam": 2025, "diem_thpt": 15.0, "diem_hocba": 18.0, "diem_dgnl": 500, "diem_vsat": 225}
]
